setup.py
ddistri/Binomialdistribution.py
ddistri/Gaussiandistribution.py
ddistri/Generaldistribution.py
ddistri/__init__.py
ddistri.egg-info/PKG-INFO
ddistri.egg-info/SOURCES.txt
ddistri.egg-info/dependency_links.txt
ddistri.egg-info/not-zip-safe
ddistri.egg-info/top_level.txt